memento/__init__.py
memento/memento.py
memento_project-0.2.dist-info/DESCRIPTION.rst
memento_project-0.2.dist-info/METADATA
memento_project-0.2.dist-info/RECORD
memento_project-0.2.dist-info/WHEEL
memento_project-0.2.dist-info/metadata.json
memento_project-0.2.dist-info/top_level.txt
