Metadata-Version: 2.0
Name: memento-project
Version: 0.2
Summary: Create checkpoints and rollback for your data
Home-page: https://github.com/LordFeratum/memento
Author: Enrique Pina Monserrat
Author-email: lord.feratum@gmail.com
License: UNKNOWN
Download-URL: https://github.com/LordFeratum/memento/archive/0.2.tar.gz
Keywords: data,python
Platform: UNKNOWN
